pictureshow/__init__.py
pictureshow/__main__.py
pictureshow/backends.py
pictureshow/cli.py
pictureshow/core.py
pictureshow/exceptions.py
pictureshow-0.14.0.dist-info/METADATA
pictureshow-0.14.0.dist-info/WHEEL
pictureshow-0.14.0.dist-info/entry_points.txt
pictureshow-0.14.0.dist-info/licenses/LICENSE
pictureshow-0.14.0.dist-info/RECORD
