Metadata-Version: 2.4
Name: pictureshow
Version: 0.14.0
Summary: Save pictures to PDF.
License-Expression: MIT
License-File: LICENSE
Author: Michal Porteš
Author-email: michalportes1@gmail.com
Requires-Python: >=3.10,<4.0
Classifier: Development Status :: 4 - Beta
Classifier: Operating System :: OS Independent
Classifier: Programming Language :: Python :: 3
Classifier: Programming Language :: Python :: 3.10
Classifier: Programming Language :: Python :: 3.11
Classifier: Programming Language :: Python :: 3.12
Classifier: Programming Language :: Python :: 3.13
Classifier: Programming Language :: Python :: 3.14
Classifier: Topic :: Software Development :: Libraries :: Python Modules
Requires-Dist: pillow (>=12,<13)
Requires-Dist: platformdirs (>=4,<5)
Requires-Dist: reportlab (>=4,<5)
Project-URL: Homepage, https://github.com/mportesdev/pictureshow
